{
  "data": [
    {
      "id": "2016048837980",
      "attributes": {
        "hidden": true,
        "short": "AEM Ph1",
        "long": "Adobe Experience Manager",
        "x": null,
        "w": null,
        "phases": "",
        "background": "F9A"
      },
      "type": "assignments"
    },
    {
      "id": "201606151959434",
      "attributes": {
        "hidden": false,
        "short": "AEM Ph2",
        "long": "Adobe Experience Manager",
        "x": 0,
        "w": 165,
        "phases": "<div data-type=\"tile\" data-stamp=\"true\" data-phase=\"PRD\" data-x=\"90\" data-y=\"0\"></div>",
        "background": "E9D"
      },
      "type": "assignments"
    },
    {
      "id": "2016048842653",
      "attributes": {
        "hidden": false,
        "short": "EB3",
        "long": "CIBC Migration Ph1",
        "x": 0,
        "w": 330,
        "rows": 3,
        "phases": "<div data-type=\"tile\" data-stamp=\"true\" data-phase=\"WTY\" data-x=\"270\" data-y=\"30\" data-width=\"60\"><div class=\"duration\" data-weeks=\"4\"></div></div><div data-type=\"tile\" data-stamp=\"true\" data-phase=\"PLT\" data-x=\"90\" data-y=\"30\" data-startson=\"W\" data-width=\"0\" data-padding=\"1\" data-num=\"2\" class=\"\"><div class=\"startsOn\" data-startson=\"W\"></div><div class=\"duration\" data-days=\"1\" data-weeks=\"0\"></div></div><div data-type=\"tile\" data-stamp=\"true\" data-phase=\"PLT\" data-x=\"135\" data-y=\"75\" data-startson=\"S\" data-width=\"0\" data-padding=\"1\" data-num=\"3\"><div class=\"startsOn\" data-startson=\"S\"></div><div class=\"duration\" data-days=\"1\" data-weeks=\"0\"></div></div><div data-type=\"tile\" data-stamp=\"true\" data-phase=\"PLT\" data-x=\"150\" data-y=\"45\" data-num=\"4\" data-startson=\"S\" data-width=\"0\" data-padding=\"1\"><div class=\"startsOn\" data-startson=\"S\"></div><div class=\"duration\" data-days=\"1\" data-weeks=\"0\"></div></div><div data-type=\"tile\" data-stamp=\"true\" data-phase=\"PLT\" data-x=\"75\" data-y=\"0\" data-startson=\"R\" data-num=\"1\" data-padding=\"1\" data-width=\"0\"><div class=\"startsOn\" data-startson=\"R\"></div><div class=\"duration\" data-days=\"1\" data-weeks=\"0\"></div></div><div data-type=\"tile\" data-stamp=\"true\" data-phase=\"PLT\" data-x=\"150\" data-y=\"15\" data-startson=\"W\" data-width=\"0\" data-padding=\"1\" data-num=\"6\"><div class=\"startsOn\" data-startson=\"W\"></div><div class=\"duration\" data-days=\"1\" data-weeks=\"0\"></div></div><div data-type=\"tile\" data-stamp=\"true\" data-phase=\"PLT\" data-x=\"150\" data-y=\"75\" data-startson=\"F\" data-width=\"0\" data-padding=\"1\" data-num=\"7\"><div class=\"startsOn\" data-startson=\"F\"></div><div class=\"duration\" data-days=\"1\" data-weeks=\"0\"></div></div><div data-type=\"tile\" data-stamp=\"true\" data-phase=\"PLT\" data-x=\"165\" data-y=\"45\" data-startson=\"W\" data-num=\"8\" data-width=\"0\" data-padding=\"1\" class=\"\"><div class=\"startsOn\" data-startson=\"W\"></div><div class=\"duration\" data-days=\"1\" data-weeks=\"0\"></div></div><div data-type=\"tile\" data-stamp=\"true\" data-phase=\"FRZ\" data-x=\"180\" data-y=\"0\" data-startson=\"S\" data-width=\"15\"><div class=\"startsOn\" data-startson=\"S\"></div><div class=\"duration\" data-weeks=\"1\"></div></div><div data-type=\"tile\" data-stamp=\"true\" data-phase=\"PRD\" data-x=\"255\" data-y=\"60\" data-startson=\"F\" data-width=\"0\" data-padding=\"1\" class=\"\"><div class=\"startsOn\" data-startson=\"F\"></div><div class=\"duration\" data-days=\"1\" data-weeks=\"0\"></div><div class=\"desc\"></div></div>",
        "background": "99A"
      },
      "type": "assignments"
    },
    {
      "id": "201608071658185",
      "attributes": {
        "hidden": false,
        "short": "eCM",
        "long": "eBanking Content Management : Admin App",
        "x": 0,
        "w": 330,
        "rows": null,
        "phases": "<div data-type=\"tile\" data-stamp=\"true\" data-phase=\"PRD\" data-x=\"255\" data-y=\"0\" data-startson=\"F\" data-width=\"0\" data-padding=\"1\"><div class=\"startsOn\" data-startson=\"F\"></div><div class=\"duration\" data-days=\"1\"></div></div><div data-type=\"tile\" data-stamp=\"true\" data-phase=\"PLT\" data-x=\"45\" data-y=\"0\"></div><div data-type=\"tile\" data-stamp=\"true\" data-phase=\"SPR\" data-x=\"15\" data-y=\"0\"></div><div data-type=\"tile\" data-stamp=\"true\" data-phase=\"SPR\" data-x=\"75\" data-y=\"0\"></div><div data-type=\"tile\" data-stamp=\"true\" data-phase=\"SPR\" data-x=\"120\" data-y=\"0\"></div><div data-type=\"tile\" data-stamp=\"true\" data-phase=\"WTY\" data-x=\"270\" data-y=\"30\" data-width=\"60\" class=\"\"><div class=\"duration\" data-weeks=\"4\"></div></div>",
        "background": "FDE123"
      },
      "type": "assignments"
    },
    {
      "id": "2016048843545",
      "attributes": {
        "hidden": false,
        "short": "EB4",
        "long": "CiBC Migration Ph2",
        "x": 120,
        "w": 465,
        "rows": null,
        "phases": "<div data-type=\"tile\" data-stamp=\"true\" data-phase=\"REQ\" data-x=\"120\" data-y=\"0\"></div><div data-type=\"tile\" data-stamp=\"true\" data-customphase=\"true\" data-x=\"195\" data-y=\"0\" data-phase=\"GIC\" data-width=\"180\"><div class=\"duration\" data-weeks=\"12\"></div></div>",
        "background": "899AFF"
      },
      "type": "assignments"
    },
    {
      "id": "201608071515916",
      "attributes": {
        "hidden": false,
        "short": "ITC",
        "long": "Integrated Tax Compliance",
        "x": 0,
        "w": 585,
        "rows": null,
        "phases": "<div data-type=\"tile\" data-stamp=\"true\" data-phase=\"PRD\" data-x=\"510\" data-y=\"0\"></div>",
        "background": "ABBCAC"
      },
      "type": "assignments"
    },
    {
      "id": "201701061345380",
      "attributes": {
        "hidden": false,
        "short": "P2P 1",
        "long": "Send/Respond to Money Request",
        "x": 45,
        "w": 555,
        "rows": 9,
        "phases": "<div data-type=\"tile\" data-stamp=\"true\" data-phase=\"UAT\" data-x=\"360\" data-y=\"0\" data-width=\"45\"><div class=\"duration\" data-weeks=\"3\"></div></div><div data-type=\"tile\" data-stamp=\"true\" data-phase=\"PLT\" data-x=\"525\" data-y=\"15\" data-width=\"30\"><div class=\"duration\" data-weeks=\"2\"></div></div><div data-type=\"tile\" data-stamp=\"true\" data-phase=\"FRZ\" data-x=\"480\" data-y=\"0\" data-width=\"45\" data-colour=\"FFE32F\"><div class=\"duration\" data-weeks=\"3\"></div></div><div data-type=\"tile\" data-stamp=\"true\" data-phase=\"PRD\" data-x=\"540\" data-y=\"30\" data-width=\"0\" data-padding=\"1\"><div class=\"duration\" data-days=\"1\" data-weeks=\"0\"></div></div><div data-type=\"tile\" data-stamp=\"true\" data-phase=\"WTY\" data-x=\"540\" data-y=\"60\" data-width=\"60\"><div class=\"duration\" data-weeks=\"4\"></div></div><div data-type=\"tile\" data-stamp=\"true\" data-phase=\"REQ\" data-x=\"45\" data-y=\"0\"></div><div data-type=\"tile\" data-stamp=\"true\" data-phase=\"SPR\" data-x=\"195\" data-y=\"30\" data-num=\"1\" data-width=\"30\" data-colour=\"F86D72\" class=\"\"><div class=\"desc\" data-long=\"Ember\">EM</div><div class=\"details\"><div>GIT repo setup</div><div>Content SVN strategy</div><div>JIRA setup / access</div><div>Finalize APIs</div><div>Update existing send money flow for auto-deposit (CIBC only)</div></div><div class=\"duration\" data-weeks=\"2\"></div></div><div data-type=\"tile\" data-stamp=\"true\" data-phase=\"SPR\" data-x=\"225\" data-y=\"45\" data-num=\"2\" data-width=\"30\" data-colour=\"F86D72\"><div class=\"desc\" data-long=\"\">EM</div><div class=\"details\"><div>Continue send money flow for auto-deposit (CIBC &amp; PCF)</div><div>Fulfill money request - new flow (CIBC only)</div></div><div class=\"duration\" data-weeks=\"2\"></div></div><div data-type=\"tile\" data-stamp=\"true\" data-phase=\"SPR\" data-x=\"255\" data-y=\"30\" data-num=\"3\" data-width=\"30\" data-colour=\"F86D72\"><div class=\"desc\" data-long=\"\">EM</div><div class=\"duration\" data-weeks=\"2\"></div><div class=\"details\"><div>Continue fulfill money request - (CIBC &amp; PCF)</div><div>In-depth browser testing</div><div>In-depth accessibility testing</div></div></div><div data-type=\"tile\" data-stamp=\"true\" data-phase=\"Backend\" data-customphase=\"true\" data-x=\"225\" data-y=\"120\" data-width=\"45\"><div class=\"duration\" data-weeks=\"3\"></div><div class=\"desc\" data-long=\"Integration\">Int</div></div><div data-type=\"tile\" data-stamp=\"true\" data-customphase=\"true\" data-x=\"195\" data-y=\"105\" data-phase=\"API Testing\" data-width=\"105\"><div class=\"duration\" data-weeks=\"7\"></div></div><div data-type=\"tile\" data-stamp=\"true\" data-phase=\"SIT\" data-x=\"270\" data-y=\"90\" data-width=\"30\" class=\"\"><div class=\"desc\" data-long=\"Shakedown\">SD</div><div class=\"duration\" data-weeks=\"2\"></div></div><div data-type=\"tile\" data-stamp=\"true\" data-phase=\"SIT\" data-x=\"300\" data-y=\"90\" data-width=\"60\"><div class=\"duration\" data-weeks=\"4\"></div><div class=\"desc\">EUF</div></div><div data-type=\"tile\" data-stamp=\"true\" data-phase=\"Pen Test\" data-customphase=\"true\" data-x=\"330\" data-y=\"60\" data-width=\"30\" class=\"\"><div class=\"duration\" data-weeks=\"2\"></div></div><div data-type=\"tile\" data-stamp=\"true\" data-phase=\"UAT\" data-x=\"345\" data-y=\"15\" data-width=\"15\"><div class=\"desc\" data-long=\"Shakedown\">SD</div><div class=\"duration\" data-weeks=\"1\"></div></div><div data-type=\"tile\" data-stamp=\"true\" data-phase=\"UAT\" data-x=\"405\" data-y=\"15\" data-width=\"45\"><div class=\"desc\">RBSS</div><div class=\"duration\" data-weeks=\"3\"></div></div><div data-type=\"tile\" data-stamp=\"true\" data-phase=\"PTE\" data-customphase=\"true\" data-x=\"420\" data-y=\"30\" data-width=\"60\"><div class=\"duration\" data-weeks=\"4\"></div></div><div data-type=\"tile\" data-stamp=\"true\" data-phase=\"PTE\" data-customphase=\"true\" data-x=\"390\" data-y=\"45\" data-width=\"30\"><div class=\"desc\">Pre</div><div class=\"duration\" data-weeks=\"2\"></div></div><div data-type=\"tile\" data-stamp=\"true\" data-phase=\"SIT\" data-x=\"195\" data-y=\"150\" data-num=\"1\" data-width=\"45\" data-colour=\"ABCEEE\"><div class=\"desc\">RBSS ATs</div><div class=\"duration\" data-weeks=\"3\"></div><div class=\"details\"><div>API testing in lieu of front-end</div></div></div><div data-type=\"tile\" data-stamp=\"true\" data-phase=\"SIT\" data-x=\"240\" data-y=\"150\" data-num=\"2\" data-width=\"45\" data-colour=\"ABCEEE\"><div class=\"desc\">RBSS</div><div class=\"duration\" data-weeks=\"3\"></div></div><div data-type=\"tile\" data-stamp=\"true\" data-phase=\"PAT\" data-x=\"390\" data-y=\"150\" data-colour=\"ABCEEE\" data-width=\"45\"><div class=\"desc\">RBSS</div><div class=\"duration\" data-weeks=\"3\"></div></div><div data-type=\"tile\" data-stamp=\"true\" data-phase=\"UAT\" data-x=\"390\" data-y=\"165\" data-width=\"45\" data-colour=\"ABCEEE\"><div class=\"desc\">RBSS</div><div class=\"duration\" data-weeks=\"3\"></div></div><div data-type=\"tile\" data-stamp=\"true\" data-phase=\"PRD\" data-x=\"465\" data-y=\"150\" data-width=\"0\" data-padding=\"1\" data-colour=\"ABCEEE\" class=\"\"><div class=\"desc\">RBSS</div><div class=\"duration\" data-days=\"1\"></div></div><div data-type=\"tile\" data-stamp=\"true\" data-phase=\"SPR\" data-x=\"225\" data-y=\"75\" data-num=\"1\" data-width=\"45\" data-colour=\"8CBA19\" class=\"\"><div class=\"desc\" data-long=\"Mobi-web\">MB</div><div class=\"duration\" data-weeks=\"3\"></div><div class=\"details\"><div>1 week overlap with wicket devs needed</div></div></div><div data-type=\"tile\" data-stamp=\"true\" data-customphase=\"true\" data-x=\"270\" data-y=\"180\" data-phase=\"RBSS\" data-width=\"90\" data-colour=\"ADD2E2\"><div class=\"desc\" data-long=\"\">SIT Support</div><div class=\"duration\" data-weeks=\"6\"></div><div class=\"details\"><div>RBSS support for DT during SIT</div></div></div><div data-type=\"tile\" data-stamp=\"true\" data-phase=\"SPR\" data-x=\"285\" data-y=\"45\" data-colour=\"F86D72\" data-num=\"4\" data-width=\"30\"><div class=\"desc\">EM</div><div class=\"duration\" data-weeks=\"2\"></div></div><div data-type=\"tile\" data-stamp=\"true\" data-customphase=\"true\" data-x=\"195\" data-y=\"0\" data-phase=\"Send Money\" data-width=\"60\"><div class=\"duration\" data-weeks=\"4\"></div></div><div data-type=\"tile\" data-stamp=\"true\" data-customphase=\"true\" data-x=\"225\" data-y=\"15\" data-phase=\"Fulfill Request\" data-width=\"60\"><div class=\"duration\" data-weeks=\"4\"></div></div>",
        "background": "CF92F0"
      },
      "type": "assignments"
    },
    {
      "id": "201701061342358",
      "attributes": {
        "hidden": false,
        "short": "RTCCT",
        "long": "Real Time Credit Card Txn",
        "x": 0,
        "w": 675,
        "rows": 2,
        "phases": "<div data-type=\"tile\" data-stamp=\"true\" data-phase=\"SPR\" data-x=\"270\" data-y=\"0\" data-num=\"1\" data-width=\"15\" data-startson=\"T\" data-padding=\"4\"><div class=\"desc\" data-long=\"eBanking\">EB</div><div class=\"duration\" data-weeks=\"1\" data-days=\"4\"></div><div class=\"startsOn\" data-startson=\"T\"></div></div><div data-type=\"tile\" data-stamp=\"true\" data-phase=\"SPR\" data-x=\"300\" data-y=\"0\" data-num=\"2\" data-width=\"15\" data-padding=\"4\"><div class=\"duration\" data-weeks=\"1\" data-days=\"4\"></div><div class=\"desc\" data-long=\"Front End\">FE</div></div><div data-type=\"tile\" data-stamp=\"true\" data-phase=\"REQ\" data-x=\"120\" data-y=\"0\"></div><div data-type=\"tile\" data-stamp=\"true\" data-phase=\"SPR\" data-x=\"330\" data-y=\"0\" data-width=\"30\" data-padding=\"1\" data-num=\"3\"><div class=\"duration\" data-weeks=\"2\" data-days=\"1\"></div><div class=\"desc\" data-long=\"Integration\">Int</div></div><div data-type=\"tile\" data-stamp=\"true\" data-phase=\"DIT\" data-x=\"300\" data-y=\"45\" data-width=\"15\" data-padding=\"4\"><div class=\"duration\" data-weeks=\"1\" data-days=\"4\"></div></div><div data-type=\"tile\" data-stamp=\"true\" data-phase=\"SIT\" data-x=\"330\" data-y=\"30\" data-width=\"30\" data-padding=\"1\"><div class=\"duration\" data-weeks=\"2\" data-days=\"1\"></div><div class=\"desc\" data-long=\"Simulator\">Sim</div></div><div data-type=\"tile\" data-stamp=\"true\" data-phase=\"SIT\" data-x=\"360\" data-y=\"60\" data-startson=\"T\" data-width=\"60\"><div class=\"startsOn\" data-startson=\"T\"></div><div class=\"duration\" data-weeks=\"4\"></div><div class=\"desc\" data-long=\"End to end\">E2E</div></div><div data-type=\"tile\" data-stamp=\"true\" data-phase=\"SIT\" data-x=\"420\" data-y=\"30\" data-startson=\"T\" data-width=\"30\" class=\"\"><div class=\"desc\" data-long=\"Clean Management\">CM</div><div class=\"startsOn\" data-startson=\"T\"></div><div class=\"duration\" data-weeks=\"2\"></div></div><div data-type=\"tile\" data-stamp=\"true\" data-phase=\"UAT\" data-x=\"450\" data-y=\"0\" data-width=\"30\" data-padding=\"2\"><div class=\"duration\" data-weeks=\"2\" data-days=\"2\"></div></div><div data-type=\"tile\" data-stamp=\"true\" data-phase=\"BAT\" data-x=\"480\" data-y=\"15\" data-startson=\"W\" data-width=\"60\" data-padding=\"2\"><div class=\"startsOn\" data-startson=\"W\"></div><div class=\"duration\" data-weeks=\"4\" data-days=\"2\"></div></div><div data-type=\"tile\" data-stamp=\"true\" data-phase=\"FRZ\" data-x=\"540\" data-y=\"30\" data-startson=\"R\" data-width=\"30\"><div class=\"startsOn\" data-startson=\"R\"></div><div class=\"duration\" data-weeks=\"2\"></div></div><div data-type=\"tile\" data-stamp=\"true\" data-phase=\"PLT\" data-x=\"570\" data-y=\"60\" data-startson=\"R\" data-width=\"15\" data-padding=\"2\" class=\"\"><div class=\"startsOn\" data-startson=\"R\"></div><div class=\"duration\" data-weeks=\"1\" data-days=\"2\"></div></div><div data-type=\"tile\" data-stamp=\"true\" data-phase=\"PRD\" data-x=\"600\" data-y=\"30\" data-startson=\"S\" data-width=\"0\" data-padding=\"1\" class=\"\"><div class=\"startsOn\" data-startson=\"S\"></div><div class=\"desc\" data-long=\"\">C</div><div class=\"duration\" data-days=\"1\" data-weeks=\"0\"></div></div><div data-type=\"tile\" data-stamp=\"true\" data-phase=\"PRD\" data-x=\"600\" data-y=\"0\" data-width=\"0\" data-padding=\"1\"><div class=\"desc\" data-long=\"\">iOS</div><div class=\"duration\" data-days=\"1\" data-weeks=\"0\"></div></div><div data-type=\"tile\" data-stamp=\"true\" data-phase=\"WTY\" data-x=\"600\" data-y=\"75\" data-startson=\"W\" data-width=\"60\" data-padding=\"3\"><div class=\"startsOn\" data-startson=\"W\"></div><div class=\"duration\" data-weeks=\"4\" data-days=\"3\"></div></div><div data-type=\"tile\" data-stamp=\"true\" data-customphase=\"true\" data-x=\"405\" data-y=\"75\" data-phase=\"MLIDT\" data-width=\"75\" data-colour=\"3E97CF\"><div class=\"duration\" data-weeks=\"5\"></div></div>",
        "background": "D1E100"
      },
      "type": "assignments"
    },
    {
      "id": "20160807151538",
      "attributes": {
        "hidden": false,
        "short": "DSDB",
        "long": "Digital Safety Deposit Box",
        "x": 0,
        "w": 705,
        "rows": 8,
        "phases": "<div data-type=\"tile\" data-stamp=\"true\" data-phase=\"SPR\" data-x=\"90\" data-y=\"30\" data-width=\"45\" data-num=\"1\" class=\"\"><div class=\"duration\" data-weeks=\"3\"></div><div class=\"desc\" data-long=\"\">FE</div><div class=\"details\"><div>IA agreement with mid-tier</div><div>POC to open DSDB app in same window</div><div>Setup environments</div><div>GIT repo setup for addon &amp; standalone-app</div><div>Solution design</div><div>Install kits</div></div></div><div data-type=\"tile\" data-stamp=\"true\" data-phase=\"SPR\" data-x=\"135\" data-y=\"60\" data-width=\"30\" data-num=\"2\"><div class=\"duration\" data-weeks=\"2\"></div><div class=\"desc\" data-long=\"\">FE</div><div class=\"details\"><div>Install Foundation &amp; setup SCSS structure</div><div>DV Landing page</div><div>Retrieve &amp; display folders</div><div>Retrieve &amp; display recent docs</div><div>Display on-boarding notice</div></div></div><div data-type=\"tile\" data-stamp=\"true\" data-phase=\"SPR\" data-x=\"165\" data-y=\"30\" data-width=\"30\" data-num=\"3\"><div class=\"duration\" data-weeks=\"2\"></div><div class=\"desc\" data-long=\"\">FE</div><div class=\"details\"><div>Retrieve &amp; display PDF doc in viewer</div><div>Display brochure list from JSON</div></div></div><div data-type=\"tile\" data-stamp=\"true\" data-phase=\"SPR\" data-x=\"195\" data-y=\"60\" data-width=\"30\" data-num=\"4\"><div class=\"duration\" data-weeks=\"2\"></div><div class=\"desc\" data-long=\"\">FE</div><div class=\"details\"><div>Folder view</div></div></div><div data-type=\"tile\" data-stamp=\"true\" data-phase=\"SPR\" data-x=\"225\" data-y=\"30\" data-num=\"5\" data-width=\"30\"><div class=\"desc\" data-long=\"\">FE</div><div class=\"duration\" data-weeks=\"2\"></div><div class=\"details\"><div>Refactor</div><div>Update DSDB stand-alone app &amp; EB3 codebase to consume new app</div><div>Mock data into EB3 codebase</div><div>Update DSR to point to DSDB app</div></div></div><div data-type=\"tile\" data-stamp=\"true\" data-phase=\"SPR\" data-x=\"255\" data-y=\"60\" data-num=\"6\" data-width=\"30\"><div class=\"desc\" data-long=\"\">FE</div><div class=\"duration\" data-weeks=\"2\"></div><div class=\"details\"><div>Device &amp; Browser testing</div><div>Run 20% of QC test cases</div><div>Provide DIT release notes for QA</div></div></div><div data-type=\"tile\" data-stamp=\"true\" data-phase=\"SPR\" data-x=\"285\" data-y=\"30\" data-num=\"7\" data-width=\"30\"><div class=\"desc\" data-long=\"\">FE</div><div class=\"duration\" data-weeks=\"2\"></div><div class=\"details\"><div>Happy &amp; alternate flow</div><div>Add / update / delete</div></div></div><div data-type=\"tile\" data-stamp=\"true\" data-phase=\"SPR\" data-x=\"315\" data-y=\"60\" data-num=\"8\" data-width=\"30\"><div class=\"desc\" data-long=\"\">FE</div><div class=\"duration\" data-weeks=\"2\"></div><div class=\"details\"><div>CMS keys for alerts</div><div>Add DSDB on \"Manage My Alerts\"</div><div>Error pages</div></div></div><div data-type=\"tile\" data-stamp=\"true\" data-phase=\"SPR\" data-x=\"345\" data-y=\"30\" data-num=\"9\" data-width=\"30\"><div class=\"desc\" data-long=\"\">FE</div><div class=\"duration\" data-weeks=\"2\"></div><div class=\"details\"><div>Device &amp; browser testing</div><div>Code refactor</div></div></div><div data-type=\"tile\" data-stamp=\"true\" data-phase=\"DIT\" data-x=\"255\" data-y=\"105\" data-width=\"60\" data-colour=\"FEC037\" data-startson=\"F\"><div class=\"duration\" data-weeks=\"4\"></div><div class=\"startsOn\" data-startson=\"F\"></div></div><div data-type=\"tile\" data-stamp=\"true\" data-phase=\"SIT\" data-x=\"315\" data-y=\"105\" data-startson=\"F\" data-width=\"45\" data-num=\"1\"><div class=\"duration\" data-weeks=\"3\"></div><div class=\"startsOn\" data-startson=\"F\"></div></div><div data-type=\"tile\" data-stamp=\"true\" data-phase=\"SIT\" data-x=\"360\" data-y=\"105\" data-startson=\"F\" data-width=\"45\" data-num=\"2\"><div class=\"desc\" data-long=\"\"></div><div class=\"duration\" data-weeks=\"3\"></div><div class=\"startsOn\" data-startson=\"F\"></div></div><div data-type=\"tile\" data-stamp=\"true\" data-phase=\"UAT\" data-x=\"435\" data-y=\"60\" data-width=\"30\" data-startson=\"R\" data-num=\"1\"><div class=\"duration\" data-weeks=\"2\"></div><div class=\"desc\" data-long=\"\"></div><div class=\"startsOn\" data-startson=\"R\"></div></div><div data-type=\"tile\" data-stamp=\"true\" data-phase=\"PLT\" data-x=\"540\" data-y=\"0\" data-width=\"30\" data-startson=\"S\"><div class=\"duration\" data-weeks=\"2\"></div><div class=\"startsOn\" data-startson=\"S\"></div></div><div data-type=\"tile\" data-stamp=\"true\" data-phase=\"PRD\" data-x=\"630\" data-y=\"15\" data-startson=\"S\" data-width=\"0\" data-padding=\"1\"><div class=\"startsOn\" data-startson=\"S\"></div><div class=\"desc\" data-long=\"Front End\">FE</div><div class=\"duration\" data-days=\"1\" data-weeks=\"0\"></div></div><div data-type=\"tile\" data-stamp=\"true\" data-phase=\"WTY\" data-x=\"630\" data-y=\"45\" data-width=\"75\"><div class=\"duration\" data-weeks=\"5\"></div></div><div data-type=\"tile\" data-stamp=\"true\" data-phase=\"UAT\" data-x=\"465\" data-y=\"30\" data-startson=\"R\" data-width=\"30\" data-padding=\"2\"><div class=\"desc\" data-long=\"\">CM</div><div class=\"startsOn\" data-startson=\"R\"></div><div class=\"duration\" data-weeks=\"2\" data-days=\"2\"></div></div><div data-type=\"tile\" data-stamp=\"true\" data-phase=\"SIT\" data-x=\"405\" data-y=\"105\" data-startson=\"F\" data-width=\"45\" data-num=\"3\"><div class=\"startsOn\" data-startson=\"F\"></div><div class=\"duration\" data-weeks=\"3\"></div><div class=\"desc\"></div></div><div data-type=\"tile\" data-stamp=\"true\" data-phase=\"PKG\" data-customphase=\"true\" data-x=\"135\" data-y=\"0\" data-width=\"150\" data-num=\"1\" data-colour=\"F86D72\"><div class=\"duration\" data-weeks=\"10\"></div><div class=\"desc\">FE</div></div><div data-type=\"tile\" data-stamp=\"true\" data-phase=\"PKG\" data-customphase=\"true\" data-x=\"285\" data-y=\"0\" data-width=\"90\" data-num=\"2\" data-colour=\"D773B3\"><div class=\"duration\" data-weeks=\"6\"></div><div class=\"desc\">FE</div></div><div data-type=\"tile\" data-stamp=\"true\" data-customphase=\"true\" data-x=\"255\" data-y=\"30\" data-phase=\"Int Testing\" data-width=\"30\" data-colour=\"F86D72\"><div class=\"duration\" data-weeks=\"2\"></div></div><div data-type=\"tile\" data-stamp=\"true\" data-customphase=\"true\" data-x=\"345\" data-y=\"60\" data-phase=\"Int Testing\" data-width=\"30\" data-colour=\"D773B3\"><div class=\"duration\" data-weeks=\"2\"></div></div><div data-type=\"tile\" data-stamp=\"true\" data-phase=\"PRD\" data-x=\"360\" data-y=\"135\" data-width=\"0\" data-padding=\"1\" data-colour=\"FE7B23\"><div class=\"desc\" data-long=\"\">RBSS</div><div class=\"duration\" data-days=\"1\"></div><div class=\"details\"><div>Confirmed - API testing in lieu of front-end</div></div></div><div data-type=\"tile\" data-stamp=\"true\" data-phase=\"Compass\" data-customphase=\"true\" data-x=\"315\" data-y=\"165\" data-colour=\"8CBA19\" data-width=\"90\" data-startson=\"S\" data-padding=\"1\"><div class=\"desc\" data-long=\"Performance Testing\">PTE</div><div class=\"details\"><div>MLIDT</div><div>ECM</div></div><div class=\"duration\" data-weeks=\"6\" data-days=\"1\"></div><div class=\"startsOn\" data-startson=\"S\"></div></div><div data-type=\"tile\" data-stamp=\"true\" data-phase=\"PRD\" data-x=\"570\" data-y=\"15\" data-startson=\"S\" data-padding=\"1\" data-width=\"0\"><div class=\"desc\" data-long=\"eBanking\">EB</div><div class=\"startsOn\" data-startson=\"S\"></div><div class=\"duration\" data-days=\"1\" data-weeks=\"0\"></div></div><div data-type=\"tile\" data-stamp=\"true\" data-phase=\"PTE\" data-customphase=\"true\" data-x=\"495\" data-y=\"0\" data-width=\"30\"><div class=\"duration\" data-weeks=\"2\"></div></div>",
        "background": "CACBBA"
      },
      "type": "assignments"
    },
    {
      "id": "201609270741658",
      "attributes": {
        "hidden": false,
        "short": "BI",
        "long": "Base Initiatives",
        "x": 120,
        "w": 465,
        "rows": 4,
        "phases": "<div data-type=\"tile\" data-stamp=\"true\" data-phase=\"Ember Engines\" data-customphase=\"true\" data-x=\"330\" data-y=\"0\" data-width=\"195\" data-colour=\"3E97CF\"><div class=\"duration\" data-weeks=\"13\"></div><div class=\"desc\"></div><div class=\"details\"><div>Ken Buck</div></div></div><div data-type=\"tile\" data-stamp=\"true\" data-phase=\"CI Server Upgrade\" data-customphase=\"true\" data-x=\"330\" data-y=\"90\" data-width=\"195\" class=\"\"><div class=\"duration\" data-weeks=\"13\"></div><div class=\"desc\"></div><div class=\"details\"><div>Kyle &nbsp;Lu</div></div></div><div data-type=\"tile\" data-stamp=\"true\" data-phase=\"SVN to GIT\" data-customphase=\"true\" data-x=\"195\" data-y=\"105\" data-colour=\"AB4189\" data-width=\"195\"><div class=\"duration\" data-weeks=\"13\"></div><div class=\"details\"><div>Aleem</div></div></div><div data-type=\"tile\" data-stamp=\"true\" data-customphase=\"true\" data-x=\"210\" data-y=\"15\" data-phase=\"Prereq : 2.8+\" data-width=\"105\" data-colour=\"3E97CF\"><div class=\"details\"><div>Upgrade banking app from 1.13 to 2.8+</div><div>Upgrade all kits being consumed to 2.8+</div></div><div class=\"duration\" data-weeks=\"7\"></div></div><div data-type=\"tile\" data-stamp=\"true\" data-phase=\"Test CI\" data-customphase=\"true\" data-x=\"315\" data-y=\"30\" data-colour=\"3E97CF\" data-width=\"15\"><div class=\"details\"><div>Content structure</div><div>JCR simulator / stubs</div><div>Identify now to run test cases for content effectively</div><div>Modularize acceptance tests</div></div><div class=\"duration\" data-weeks=\"1\"></div></div><div data-type=\"tile\" data-stamp=\"true\" data-phase=\"Create engine\" data-customphase=\"true\" data-x=\"315\" data-y=\"15\" data-colour=\"3E97CF\" data-width=\"210\"><div class=\"details\"><div>In-repo engine</div><div>Sym-link banking core</div><div>Identify common services</div><div>Copy/paste to an addon for simplicity of POC</div><div>i.e. Authenticated routes</div></div><div class=\"duration\" data-weeks=\"14\"></div></div><div data-type=\"tile\" data-stamp=\"true\" data-phase=\"GitLab to GitHub\" data-customphase=\"true\" data-x=\"330\" data-y=\"60\" data-width=\"195\" data-colour=\"8CBA19\"><div class=\"duration\" data-weeks=\"13\"></div><div class=\"details\"><div>James Ko</div></div></div>",
        "background": "FF9121"
      },
      "type": "assignments"
    },
    {
      "id": "2016048844325",
      "attributes": {
        "hidden": false,
        "short": "mQR",
        "long": "Mobile Quick Release",
        "x": 0,
        "w": 375,
        "rows": 2,
        "phases": "<div data-type=\"tile\" data-stamp=\"true\" data-customphase=\"true\" data-x=\"120\" data-y=\"0\" data-phase=\"PS\" data-width=\"30\"><div class=\"desc\" data-long=\"\">KT</div><div class=\"duration\" data-weeks=\"2\"></div><div class=\"details\"><div>Product Selector knowledge transfer for Dailies team</div></div></div><div data-type=\"tile\" data-stamp=\"true\" data-customphase=\"true\" data-x=\"120\" data-y=\"30\" data-phase=\"MWS\" data-width=\"30\"><div class=\"duration\" data-weeks=\"2\"></div><div class=\"startsOn\"></div><div class=\"details\"><div>Mobi-web setup for dailies team</div></div></div><div data-type=\"tile\" data-stamp=\"true\" data-customphase=\"true\" data-x=\"150\" data-y=\"15\" data-phase=\"Refactor\" data-width=\"30\"><div class=\"desc\" data-long=\"\">PS</div><div class=\"duration\" data-weeks=\"2\"></div><div class=\"details\"><div>Improve load times</div></div></div><div data-type=\"tile\" data-stamp=\"true\" data-customphase=\"true\" data-x=\"195\" data-y=\"0\" data-phase=\"Omniture\" data-width=\"30\"><div class=\"details\"><div>New features</div><div>Updates as per Analytics requests</div></div><div class=\"duration\" data-weeks=\"2\"></div></div><div data-type=\"tile\" data-stamp=\"true\" data-phase=\"Content &amp; Styling\" data-customphase=\"true\" data-x=\"165\" data-y=\"45\" data-width=\"30\"><div class=\"duration\" data-weeks=\"2\"></div><div class=\"details\"><div>Regression testing</div></div></div><div data-type=\"tile\" data-stamp=\"true\" data-phase=\"EB3 PLT\" data-customphase=\"true\" data-x=\"195\" data-y=\"15\" data-width=\"15\"><div class=\"duration\" data-weeks=\"1\"></div></div><div data-type=\"tile\" data-stamp=\"true\" data-phase=\"P2P\" data-customphase=\"true\" data-x=\"210\" data-y=\"45\" data-width=\"45\" data-num=\"1\"><div class=\"duration\" data-weeks=\"3\"></div><div class=\"desc\">SPR</div></div><div data-type=\"tile\" data-stamp=\"true\" data-phase=\"NAPA\" data-customphase=\"true\" data-x=\"255\" data-y=\"0\" data-width=\"30\"><div class=\"duration\" data-weeks=\"2\"></div></div><div data-type=\"tile\" data-stamp=\"true\" data-customphase=\"true\" data-x=\"285\" data-y=\"0\" data-width=\"90\" data-phase=\"NAPA cont.\" class=\"\"><div class=\"duration\" data-weeks=\"6\"></div><div class=\"details\"><div>UI Refresh</div><div>Prod fixes</div><div>NAPA mTOs</div></div></div><div data-type=\"tile\" data-stamp=\"true\" data-phase=\"P2P\" data-customphase=\"true\" data-x=\"255\" data-y=\"45\" data-num=\"1\" data-width=\"120\"><div class=\"desc\">Support</div><div class=\"duration\" data-weeks=\"8\"></div></div><div data-type=\"tile\" data-stamp=\"true\" data-phase=\"RTCCT 1\" data-customphase=\"true\" data-x=\"270\" data-y=\"75\" data-width=\"105\" class=\"\"><div class=\"duration\" data-weeks=\"7\"></div></div>",
        "background": "AA7272"
      },
      "type": "assignments"
    },
    {
      "id": "201701181316464",
      "attributes": {
        "hidden": false,
        "short": "VMe2",
        "long": "Verified.me 2",
        "x": 30,
        "w": 480,
        "rows": null,
        "phases": "<div data-type=\"tile\" data-stamp=\"true\" data-phase=\"REQ\" data-x=\"30\" data-y=\"0\" data-width=\"60\" data-padding=\"4\" data-startson=\"T\"><div class=\"duration\" data-weeks=\"4\" data-days=\"4\"></div><div class=\"startsOn\" data-startson=\"T\"></div><div class=\"desc\">BRD</div></div><div data-type=\"tile\" data-stamp=\"true\" data-phase=\"REQ\" data-x=\"90\" data-y=\"15\" data-width=\"45\" data-padding=\"4\" data-startson=\"T\"><div class=\"duration\" data-weeks=\"3\" data-days=\"4\"></div><div class=\"startsOn\" data-startson=\"T\"></div><div class=\"desc\">SRD</div></div><div data-type=\"tile\" data-stamp=\"true\" data-phase=\"SPR\" data-x=\"150\" data-y=\"30\" data-width=\"105\" data-startson=\"F\" data-padding=\"1\"><div class=\"duration\" data-weeks=\"7\" data-days=\"1\"></div><div class=\"startsOn\" data-startson=\"F\"></div></div><div data-type=\"tile\" data-stamp=\"true\" data-phase=\"DIT\" data-x=\"255\" data-y=\"0\" data-width=\"135\" data-startson=\"T\" data-padding=\"4\"><div class=\"duration\" data-weeks=\"9\" data-days=\"4\"></div><div class=\"startsOn\" data-startson=\"T\"></div></div><div data-type=\"tile\" data-stamp=\"true\" data-phase=\"PRD\" data-x=\"435\" data-y=\"0\" data-width=\"0\" data-startson=\"S\"><div class=\"startsOn\" data-startson=\"S\"></div></div><div data-type=\"tile\" data-stamp=\"true\" data-customphase=\"true\" data-x=\"375\" data-y=\"30\" data-phase=\"SK\" data-colour=\"0094AE\"><div class=\"details\"><div>SecureKey will be ready</div><div>Integration testing</div></div></div>",
        "background": "AA3E22"
      },
      "type": "assignments"
    },
    {
      "id": "201701240959652",
      "attributes": {
        "hidden": false,
        "short": "PCFR",
        "long": "Remediation",
        "x": 120,
        "w": 330,
        "rows": null,
        "phases": "<div data-type=\"tile\" data-stamp=\"true\" data-customphase=\"true\" data-x=\"135\" data-y=\"0\" data-phase=\"Intake Due\" data-width=\"45\" data-padding=\"2\"><div class=\"details\"><div>All Options assessed &amp; work effort sized</div><div>Option 1: &nbsp;Back-port from 1.13 to 1.11 (no go)</div><div>Option 2: &nbsp;Uplift from 1.11 to 1.13</div><div>Option 3: &nbsp;Wait for EB5 in 3 years (no go)</div><div>Option 4: &nbsp;Tactical - fix only raised issues</div></div><div class=\"duration\" data-weeks=\"3\" data-days=\"2\"></div></div><div data-type=\"tile\" data-stamp=\"true\" data-phase=\"Remediation\" data-customphase=\"true\" data-x=\"210\" data-y=\"0\" data-width=\"0\" data-padding=\"1\"><div class=\"details\"><div>Meet with client in Ottawa</div></div><div class=\"duration\" data-days=\"1\" data-weeks=\"0\"></div></div>",
        "background": "6099F0"
      },
      "type": "assignments"
    },
    {
      "id": "2016048844554",
      "attributes": {
        "hidden": true,
        "short": "mPFM",
        "long": "Mobile PFM",
        "x": null,
        "w": null,
        "phases": "",
        "background": "DC9999"
      },
      "type": "assignments"
    },
    {
      "id": "2016048845398",
      "attributes": {
        "hidden": true,
        "short": "R24",
        "long": "NDAO",
        "x": null,
        "w": null,
        "phases": "",
        "background": "ABC123"
      },
      "type": "assignments"
    },
    {
      "id": "2016048845352",
      "attributes": {
        "hidden": true,
        "short": "R24.1a",
        "long": "Riptide / Aventura",
        "x": null,
        "w": null,
        "phases": "",
        "background": "ABC890"
      },
      "type": "assignments"
    },
    {
      "id": "201702060824573",
      "attributes": {
        "hidden": false,
        "short": "D+H PM",
        "long": "Davis & Henderson Payment Manager",
        "x": 135,
        "w": 630,
        "rows": null,
        "phases": "<div data-type=\"tile\" data-stamp=\"true\" data-phase=\"REQ\" data-x=\"135\" data-y=\"0\" data-width=\"60\"><div class=\"desc\">BRD</div><div class=\"duration\" data-weeks=\"4\"></div></div><div data-type=\"tile\" data-stamp=\"true\" data-phase=\"BUS\" data-x=\"135\" data-y=\"30\" data-width=\"135\"><div class=\"duration\" data-weeks=\"9\"></div><div class=\"desc\">Estimates</div></div><div data-type=\"tile\" data-stamp=\"true\" data-phase=\"PRD\" data-x=\"705\" data-y=\"0\" data-width=\"0\" data-padding=\"1\" data-colour=\"D773B3\"><div class=\"duration\" data-days=\"1\" data-weeks=\"0\"></div></div><div data-type=\"tile\" data-stamp=\"true\" data-phase=\"WTY\" data-x=\"705\" data-y=\"30\" data-width=\"60\" class=\"\"><div class=\"duration\" data-weeks=\"4\"></div></div>",
        "background": "F3DDDD"
      },
      "type": "assignments"
    },
    {
      "id": "201702081259433",
      "attributes": {
        "hidden": false,
        "short": "CL",
        "long": "Cardinal",
        "x": 180,
        "w": 660,
        "rows": null,
        "phases": "<div data-type=\"tile\" data-stamp=\"true\" data-phase=\"PRD\" data-x=\"765\" data-y=\"0\" data-width=\"0\" data-padding=\"1\"><div class=\"duration\" data-days=\"1\" data-weeks=\"0\"></div></div><div data-type=\"tile\" data-stamp=\"true\" data-phase=\"WTY\" data-x=\"765\" data-y=\"30\" data-width=\"60\"><div class=\"duration\" data-weeks=\"4\"></div></div><div data-type=\"tile\" data-stamp=\"true\" data-phase=\"Dev Start?\" data-customphase=\"true\" data-x=\"315\" data-y=\"0\"></div>",
        "background": "BD2031"
      },
      "type": "assignments"
    },
    {
      "id": "201702081325539",
      "attributes": {
        "hidden": false,
        "short": "CAM 2",
        "long": "ePresentment Ph2 - eDocuments",
        "x": 180,
        "w": 660,
        "rows": null,
        "phases": "<div data-type=\"tile\" data-stamp=\"true\" data-phase=\"PRD\" data-x=\"780\" data-y=\"0\"></div><div data-type=\"tile\" data-stamp=\"true\" data-phase=\"WTY\" data-x=\"780\" data-y=\"30\" data-width=\"60\"><div class=\"duration\" data-weeks=\"4\"></div></div>",
        "background": "D80980"
      },
      "type": "assignments"
    },
    {
      "id": "201702091258310",
      "attributes": {
        "hidden": false,
        "short": "CalR",
        "long": "Calendar Redesign",
        "x": 60,
        "w": 540,
        "rows": null,
        "phases": "<div data-type=\"tile\" data-stamp=\"true\" data-phase=\"Design Sessions\" data-customphase=\"true\" data-x=\"60\" data-y=\"0\" data-width=\"105\"><div class=\"duration\" data-weeks=\"7\"></div><div class=\"details\"><div>Review of current calendar</div><div>Iterative POCs for calendar refresh</div><div>Ensure OSAB meeting time slots are considered&nbsp;</div></div></div>",
        "background": "938700"
      },
      "type": "assignments"
    },
    {
      "id": "2016048846981",
      "attributes": {
        "hidden": false,
        "short": "R24.1b",
        "long": "Prepaid / Riptide CRs / CASL",
        "x": 0,
        "w": 120,
        "phases": "<div data-type=\"tile\" data-stamp=\"true\" data-phase=\"PRD\" data-x=\"45\" data-y=\"0\"></div>",
        "background": "BCD567"
      },
      "type": "assignments"
    },
    {
      "id": "2016048846779",
      "attributes": {
        "hidden": true,
        "short": "DSR Ph1",
        "long": "Digital Service Requests",
        "x": null,
        "w": null,
        "phases": "",
        "background": "CBA123"
      },
      "type": "assignments"
    },
    {
      "id": "201606152004667",
      "attributes": {
        "hidden": true,
        "short": "DSR Ph2",
        "long": "Digital Service Requests 2",
        "x": null,
        "w": null,
        "phases": "",
        "background": "C1BC88"
      },
      "type": "assignments"
    },
    {
      "id": "201610021141955",
      "attributes": {
        "hidden": false,
        "short": "DSR Ph3",
        "long": "Digital Service Requests 3",
        "x": 0,
        "w": 105,
        "phases": "<div data-type=\"tile\" data-stamp=\"true\" data-phase=\"PRD\" data-x=\"15\" data-y=\"0\" class=\"\"></div><div data-type=\"tile\" data-stamp=\"true\" data-phase=\"WTY\" data-x=\"30\" data-y=\"15\"></div>",
        "background": "D54"
      },
      "type": "assignments"
    },
    {
      "id": "201609251842281",
      "attributes": {
        "hidden": true,
        "short": "MCEE",
        "long": "Marvel Credit Cards",
        "x": null,
        "w": null,
        "phases": "",
        "background": "009098"
      },
      "type": "assignments"
    },
    {
      "id": "2016048847918",
      "attributes": {
        "hidden": false,
        "short": "R25 OAO",
        "long": "Omni Account Open",
        "x": 0,
        "w": 120,
        "rows": null,
        "phases": "<div data-type=\"tile\" data-stamp=\"true\" data-phase=\"PRD\" data-x=\"30\" data-y=\"0\"></div>",
        "background": "CBACBA"
      },
      "type": "assignments"
    },
    {
      "id": "201604884392",
      "attributes": {
        "hidden": false,
        "short": "EB5",
        "long": "PCF Parity",
        "x": 120,
        "w": 465,
        "phases": "",
        "background": "899"
      },
      "type": "assignments"
    },
    {
      "id": "201608071516802",
      "attributes": {
        "hidden": false,
        "short": "SK",
        "long": "Secure Key",
        "x": 0,
        "w": 105,
        "phases": "<div data-type=\"tile\" data-stamp=\"true\" data-phase=\"PLT\" data-x=\"30\" data-y=\"0\"></div><div data-type=\"tile\" data-stamp=\"true\" data-phase=\"PRD\" data-x=\"30\" data-y=\"30\" class=\"\"></div><div data-type=\"tile\" data-stamp=\"true\" data-phase=\"WTY\" data-x=\"60\" data-y=\"0\"></div><div data-type=\"tile\" data-stamp=\"true\" data-phase=\"FRZ\" data-x=\"0\" data-y=\"0\"></div>",
        "background": "DFFDFF"
      },
      "type": "assignments"
    },
    {
      "id": "201608071606465",
      "attributes": {
        "hidden": false,
        "short": "C2CM",
        "long": "Click To Chat Migration",
        "x": 0,
        "w": 60,
        "phases": "<div data-type=\"tile\" data-stamp=\"true\" data-phase=\"PRD\" data-x=\"0\" data-y=\"0\" class=\"\"></div>",
        "background": "239BBB"
      },
      "type": "assignments"
    },
    {
      "id": "201608071645461",
      "attributes": {
        "hidden": false,
        "short": "OSAB",
        "long": "Online Sales Appointment Booking",
        "x": 0,
        "w": 30,
        "phases": "",
        "background": "404D00"
      },
      "type": "assignments"
    },
    {
      "id": "201608071655390",
      "attributes": {
        "hidden": true,
        "short": "YP",
        "long": "Youth Profile",
        "x": 0,
        "w": 375,
        "phases": "",
        "background": "827"
      },
      "type": "assignments"
    },
    {
      "id": "201608080819786",
      "attributes": {
        "hidden": true,
        "short": "mParity",
        "long": "Mobile Parity",
        "x": null,
        "w": null,
        "phases": "",
        "background": "999DCC"
      },
      "type": "assignments"
    },
    {
      "id": "201608171328362",
      "attributes": {
        "hidden": true,
        "short": "PCF WAPP",
        "long": "Mortgage Calc + Pre-approval",
        "x": 0,
        "w": 105,
        "phases": "<div data-type=\"tile\" data-stamp=\"true\" data-phase=\"PRD\" data-x=\"15\" data-y=\"0\"></div><div data-type=\"tile\" data-stamp=\"true\" data-phase=\"WTY\" data-x=\"45\" data-y=\"0\"></div>",
        "background": "332392"
      },
      "type": "assignments"
    },
    {
      "id": "201609251829470",
      "attributes": {
        "hidden": false,
        "short": "VMe",
        "long": "Verify Me",
        "x": 0,
        "w": 120,
        "phases": "<div data-type=\"tile\" data-stamp=\"true\" data-phase=\"PLT\" data-x=\"15\" data-y=\"0\"></div>",
        "background": "FD3E22"
      },
      "type": "assignments"
    },
    {
      "id": "201608171346689",
      "attributes": {
        "hidden": false,
        "short": "ECCO",
        "long": "Chat",
        "x": 0,
        "w": 585,
        "phases": "",
        "background": "398DFF"
      },
      "type": "assignments"
    },
    {
      "id": "201606030923307",
      "attributes": {
        "hidden": false,
        "short": "Dailies",
        "long": "Dailies",
        "background": "A0DA11",
        "phases": ""
      },
      "type": "assignments"
    },
    {
      "id": "201606030925627",
      "attributes": {
        "hidden": true,
        "short": "DO",
        "long": "Digital Optimization",
        "x": null,
        "w": null,
        "phases": "",
        "background": "D01888"
      },
      "type": "assignments"
    }
  ]
}